dp_learning_ff/__init__.py
dp_learning_ff/least_squares.py
dp_learning_ff/mechanisms.py
dp_learning_ff/prototypes.py
dp_learning_ff/utils.py
dp_learning_ff/coinpress/README.md
dp_learning_ff/coinpress/__init__.py
dp_learning_ff/coinpress/algos.py
dp_learning_ff/coinpress/utils.py
dp_learning_ff-0.0.8.dist-info/METADATA
dp_learning_ff-0.0.8.dist-info/WHEEL
dp_learning_ff-0.0.8.dist-info/licenses/LICENSE
dp_learning_ff-0.0.8.dist-info/RECORD
