Metadata-Version: 2.1
Name: dp_learning_ff
Version: 0.0.8
Summary: Repository of differentially-private methods for learning from features.
Project-URL: Repository, https://github.com/lsc64/dp-learning-from-features.git
Project-URL: Bug Tracker, https://github.com/lsc64/dp-learning-from-features/issues
Author-email: Dariush Wahdany <dariush.wahdany@aisec.fraunhofer.de>
Maintainer-email: Dariush Wahdany <dariush.wahdany@aisec.fraunhofer.de>
License:                                  Apache License
License-File: LICENSE
Keywords: ...
Classifier: Development Status :: 2 - Pre-Alpha
Classifier: Programming Language :: Python
Classifier: Programming Language :: Python :: 3 :: Only
Requires-Python: >=3.8
Requires-Dist: autodp
Requires-Dist: numpy
Requires-Dist: scikit-learn
Requires-Dist: torch
